MANIFEST.in
README.rst
setup.py
django_social_metadata.egg-info/PKG-INFO
django_social_metadata.egg-info/SOURCES.txt
django_social_metadata.egg-info/dependency_links.txt
django_social_metadata.egg-info/requires.txt
django_social_metadata.egg-info/top_level.txt
social_metadata/__init__.py
social_metadata/models.py
social_metadata/views.py
social_metadata/templates/social_metadata/default_tags.html