Metadata-Version: 1.0
Name: django-social-metadata
Version: 1.3
Summary: django-social-metadata is a Django application that provides mixin and template to display social metadata for Facebook and Google+.
Home-page: UNKNOWN
Author: Tomasz Wysocki
Author-email: tomasz@wysocki.info
License: UNKNOWN
Platform: UNKNOWN
